wagtail_pagetranslation/__init__.py
wagtail_pagetranslation/apps.py
wagtail_pagetranslation/models.py
wagtail_pagetranslation/settings.py
wagtail_pagetranslation/translation.py
wagtail_pagetranslation/wagtail_hooks.py
wagtail_pagetranslation/migrations/__init__.py
wagtail_pagetranslation/templates/translations_inline_panel.html
wagtail_pagetranslation/templates/translations_inline_panel_child.html
wagtail_pagetranslation-0.0.1.dist-info/LICENSE
wagtail_pagetranslation-0.0.1.dist-info/WHEEL
wagtail_pagetranslation-0.0.1.dist-info/METADATA
wagtail_pagetranslation-0.0.1.dist-info/RECORD
