Metadata-Version: 2.1
Name: wagtail-pagetranslation
Version: 0.0.1
Summary: Allows to translate specific pages without replicating all wagtail pages tree structure.
Author-email: Ihor Marhitych <dest81@gmail.com>, Jura Zakarija <jzakarija@ripe.net>
Requires-Python: >=3.8
Classifier: Development Status :: 3 - Alpha
Classifier: Intended Audience :: Developers
Classifier: License :: OSI Approved :: MIT License
Classifier: Operating System :: OS Independent
Classifier: Programming Language :: Python
Classifier: Programming Language :: Python :: 3
Classifier: Programming Language :: Python :: 3.8
Classifier: Programming Language :: Python :: 3.9
Classifier: Programming Language :: Python :: 3.10
Classifier: Programming Language :: Python :: 3.11
Classifier: Programming Language :: Python :: 3.12
Classifier: Framework :: Django
Classifier: Framework :: Django :: 4.2
Classifier: Framework :: Django :: 5.0
Classifier: Framework :: Wagtail
Classifier: Framework :: Wagtail :: 5
Classifier: Framework :: Wagtail :: 6
Requires-Dist: Django>=4.2
Requires-Dist: Wagtail>=5.2
Requires-Dist: tox==4.11.3 ; extra == "ci"
Requires-Dist: tox-gh-actions==3.1.3 ; extra == "ci"
Requires-Dist: dj-database-url==2.1.0 ; extra == "testing"
Requires-Dist: pre-commit==3.4.0 ; extra == "testing"
Requires-Dist: pytest==8.1.1 ; extra == "testing"
Requires-Dist: pytest-cov==5.0.0 ; extra == "testing"
Requires-Dist: pytest-django==4.8.0 ; extra == "testing"
Project-URL: Home, https://github.com/dest81/wagtail-pagetranslation
Provides-Extra: ci
Provides-Extra: testing
